__init__.py
db.py
main.py
email_to_calendar-1.0.2.dist-info/licenses/LICENSE
events/__init__.py
events/caldav.py
mail/__init__.py
mail/mail.py
mail/mail_idle.py
model/__init__.py
model/ai.py
model/email.py
model/event.py
util/__init__.py
util/ai.py
util/env.py
util/healthcheck.py
util/logging.py
util/notifications.py
email_to_calendar-1.0.2.dist-info/METADATA
email_to_calendar-1.0.2.dist-info/WHEEL
email_to_calendar-1.0.2.dist-info/top_level.txt
email_to_calendar-1.0.2.dist-info/RECORD
