Metadata-Version: 2.4
Name: email-to-calendar
Version: 1.0.2
Summary: Takes emails from an IMAP server, parses the body, and creates event(s) in a CalDAV calendar
Author-email: jnstockley <jnstockley@users.noreply.github.com>
Project-URL: Homepage, https://github.com/jnstockley/email-to-calendar
Project-URL: Repository, https://github.com/jnstockley/email-to-calendar.git
Project-URL: Issues, https://github.com/jnstockley/email-to-calendar/issues
Keywords: starter,template,python
Classifier: Programming Language :: Python :: 3
Requires-Python: <4.0,>=3.13
License-File: LICENSE
Requires-Dist: apprise==1.9.7
Requires-Dist: caldav==2.2.3
Requires-Dist: imapclient==3.1.0
Requires-Dist: markdownify==1.2.2
Requires-Dist: pydantic-ai-slim[openai]==1.47.0
Requires-Dist: pydantic-settings==2.12.0
Requires-Dist: pydantic[email]==2.12.5
Requires-Dist: sqlmodel==0.0.31
Requires-Dist: tzlocal==5.3.1
Requires-Dist: vobject==0.9.9
Requires-Dist: python-dotenv==1.2.1
Dynamic: license-file
